django_enumerify2-0.5.2.dist-info/licenses/LICENCE
enumerify/__init__.py
enumerify/enum.py
enumerify/fields.py
testproject/__init__.py
testproject/runtests.py
testproject/settings.py
testproject/testapp/__init__.py
testproject/testapp/enums.py
testproject/testapp/models.py
testproject/testapp/tests.py
django_enumerify2-0.5.2.dist-info/METADATA
django_enumerify2-0.5.2.dist-info/WHEEL
django_enumerify2-0.5.2.dist-info/top_level.txt
django_enumerify2-0.5.2.dist-info/RECORD
